alchemer/__init__.py
alchemer/classes.py
alchemer/client.py
alchemer-0.7.0.dist-info/WHEEL
alchemer-0.7.0.dist-info/METADATA
alchemer-0.7.0.dist-info/licenses/LICENSE
alchemer-0.7.0.dist-info/RECORD
